cloud_accelerator_diagnostics/__init__.py
cloud_accelerator_diagnostics/src/tensorboard_uploader/tensorboard.py
cloud_accelerator_diagnostics/src/tensorboard_uploader/uploader.py
cloud_accelerator_diagnostics/tests/tensorboard_uploader/tensorboard_test.py
cloud_accelerator_diagnostics/tests/tensorboard_uploader/uploader_test.py
cloud_accelerator_diagnostics-0.1.0.dist-info/WHEEL
cloud_accelerator_diagnostics-0.1.0.dist-info/METADATA
cloud_accelerator_diagnostics-0.1.0.dist-info/RECORD
