Metadata-Version: 2.1
Name: cloud-accelerator-diagnostics
Version: 0.1.0
Summary: Monitor, debug and profile the jobs running on Cloud accelerators like TPUs and GPUs.
Keywords: 
Author-email: Cloud TPU Team <cloud-tpu-eng@google.com>
Requires-Python: >=3.8
Classifier: Programming Language :: Python :: 3.8
Classifier: Programming Language :: Python :: 3.9
Classifier: Programming Language :: Python :: 3.10
Classifier: Programming Language :: Python :: 3.11
Requires-Dist: google-cloud-aiplatform[tensorboard]
Project-URL: Bug Tracker, https://github.com/google/cloud-accelerator-diagnostics/issues
Project-URL: Homepage, https://github.com/google/cloud-accelerator-diagnostics
